distrobuilder_menu/__init__.py
distrobuilder_menu/app.py
distrobuilder_menu/builder.py
distrobuilder_menu/templates.py
distrobuilder_menu/utils.py
distrobuilder_menu/api/__init__.py
distrobuilder_menu/api/gethub.py
distrobuilder_menu/api/singleton.py
distrobuilder_menu/api/spinner.py
distrobuilder_menu/config/__init__.py
distrobuilder_menu/config/app.py
distrobuilder_menu/config/user.py
distrobuilder_menu/menus/__init__.py
distrobuilder_menu/menus/cloudinit.py
distrobuilder_menu/menus/common.py
distrobuilder_menu/menus/helpers.py
distrobuilder_menu/menus/menuclass.py
distrobuilder_menu/menus/shared.py
distrobuilder_menu/examples/cloudinit/user-data/alpine-abuild.yaml
distrobuilder_menu/examples/cloudinit/user-data/ubuntu-gitlab.yaml
distrobuilder_menu/examples/cloudinit/user-data/ubuntu-podman.yaml
distrobuilder_menu/examples/files/alpine-abuild/cloudinit-per-once/abuild.sh
distrobuilder_menu/examples/files/alpine-abuild/home/alpine/.gitconfig
distrobuilder_menu/examples/files/alpine-abuild/home/alpine/.profile
distrobuilder_menu/examples/files/alpine-abuild/home/alpine/.vimrc
distrobuilder_menu/examples/files/alpine-abuild/home/alpine/.gnupg/gpg.conf
distrobuilder_menu/examples/files/alpine-base/etc/nanorc
distrobuilder_menu/examples/files/alpine-base/etc/apk/repositories
distrobuilder_menu/examples/files/alpine-base/etc/crontabs/root
distrobuilder_menu/examples/files/alpine-base/etc/profile.d/color_prompt.sh
distrobuilder_menu/examples/files/alpine-base/home/alpine/.profile
distrobuilder_menu/examples/files/alpine-base/root/.nanorc
distrobuilder_menu/examples/files/alpine-base/root/.profile
distrobuilder_menu/examples/files/ubuntu-base/etc/nanorc
distrobuilder_menu/examples/files/ubuntu-base/etc/apt/apt.conf.d/20auto-upgrades
distrobuilder_menu/examples/files/ubuntu-base/etc/apt/apt.conf.d/50unattended-upgrades
distrobuilder_menu/examples/files/ubuntu-base/etc/apt/sources.list.d/devel:kubic:libcontainers:unstable.list
distrobuilder_menu-0.2.9.dist-info/METADATA
distrobuilder_menu-0.2.9.dist-info/WHEEL
distrobuilder_menu-0.2.9.dist-info/entry_points.txt
distrobuilder_menu-0.2.9.dist-info/licenses/LICENSE
distrobuilder_menu-0.2.9.dist-info/RECORD
