Metadata-Version: 2.1
Name: distrobuilder_menu
Version: 0.2.9
Summary: A console frontend for Distrobuilder to build custom LXD / LXC images
Project-URL: Homepage, https://github.com/itoffshore/distrobuilder-menu
Project-URL: Bug Tracker, https://github.com/itoffshore/distrobuilder-menu/issues
Author-email: Stuart Cardall <developer@it-offshore.co.uk>
License-File: LICENSE
Classifier: License :: OSI Approved :: MIT License
Classifier: Operating System :: OS Independent
Classifier: Programming Language :: Python :: 3
Requires-Python: >=3.10
Requires-Dist: pyyaml
Requires-Dist: urllib3
